print_color_text.py
print_color_text-1.0.dist-info/WHEEL
print_color_text-1.0.dist-info/METADATA
print_color_text-1.0.dist-info/RECORD
