Metadata-Version: 2.1
Name: print-color-text
Version: 1.0
Summary: one function 'color_print(text, color)'
Author: MrBedrockpy
Author-email: aleksejorazbaev28@gmail.com
Requires-Python: >=3.9,<4.0
Classifier: Programming Language :: Python :: 3
Classifier: Programming Language :: Python :: 3.10
Classifier: Programming Language :: Python :: 3.9
